{
    "key": "group_60ed9de45cae1",
    "title": "H5P to Topic Mapping",
    "fields": [
        {
            "key": "field_60edab22b22ea",
            "label": "Question Group",
            "name": "question_group",
            "type": "repeater",
            "instructions": "",
            "required": 0,
            "conditional_logic": 0,
            "wrapper": {
                "width": "",
                "class": "",
                "id": ""
            },
            "collapsed": "field_60edab5ab22ec",
            "min": 1,
            "max": 0,
            "layout": "table",
            "button_label": "Add Link",
            "sub_fields": [
                {
                    "key": "field_60edab3db22eb",
                    "label": "xAPI Content",
                    "name": "xapi_content",
                    "type": "post_object",
                    "instructions": "",
                    "required": 0,
                    "conditional_logic": 0,
                    "wrapper": {
                        "width": "",
                        "class": "",
                        "id": ""
                    },
                    "post_type": [
                        "gb_xapi_content"
                    ],
                    "taxonomy": "",
                    "allow_null": 0,
                    "multiple": 0,
                    "return_format": "id",
                    "ui": 1
                },
                {
                    "key": "field_60edab5ab22ec",
                    "label": "Related Topic",
                    "name": "related_topic",
                    "type": "post_object",
                    "instructions": "",
                    "required": 0,
                    "conditional_logic": 0,
                    "wrapper": {
                        "width": "",
                        "class": "",
                        "id": ""
                    },
                    "post_type": [
                        "sfwd-topic"
                    ],
                    "taxonomy": "",
                    "allow_null": 0,
                    "multiple": 0,
                    "return_format": "id",
                    "ui": 1
                }
            ]
        }
    ],
    "location": [
        [
            {
                "param": "post_type",
                "operator": "==",
                "value": "sfwd-topic"
            },
            {
                "param": "post_taxonomy",
                "operator": "==",
                "value": "ld_topic_category:goal-setting"
            }
        ]
    ],
    "menu_order": 0,
    "position": "normal",
    "style": "default",
    "label_placement": "top",
    "instruction_placement": "label",
    "hide_on_screen": "",
    "active": true,
    "description": "",
    "modified": 1626188885
}