{
    "key": "group_60d4bc3227eb7",
    "title": "User Goals",
    "fields": [
        {
            "key": "field_60d4bc3966f15",
            "label": "User Goals",
            "name": "user_goals",
            "type": "repeater",
            "instructions": "",
            "required": 0,
            "conditional_logic": 0,
            "wrapper": {
                "width": "",
                "class": "",
                "id": ""
            },
            "collapsed": "",
            "min": 0,
            "max": 0,
            "layout": "row",
            "button_label": "Add Goal",
            "sub_fields": [
                {
                    "key": "field_60d4bcc38aff6",
                    "label": "Related Topic",
                    "name": "related_topic",
                    "type": "post_object",
                    "instructions": "",
                    "required": 0,
                    "conditional_logic": 0,
                    "wrapper": {
                        "width": "",
                        "class": "",
                        "id": ""
                    },
                    "post_type": [
                        "sfwd-topic"
                    ],
                    "taxonomy": "",
                    "allow_null": 0,
                    "multiple": 0,
                    "return_format": "id",
                    "ui": 1
                },
                {
                    "key": "field_60d4bc8366f17",
                    "label": "Text",
                    "name": "goal_text",
                    "type": "textarea",
                    "instructions": "",
                    "required": 0,
                    "conditional_logic": 0,
                    "wrapper": {
                        "width": "",
                        "class": "",
                        "id": ""
                    },
                    "default_value": "",
                    "placeholder": "",
                    "maxlength": "",
                    "rows": 4,
                    "new_lines": ""
                }
            ]
        }
    ],
    "location": [
        [
            {
                "param": "user_form",
                "operator": "==",
                "value": "edit"
            }
        ]
    ],
    "menu_order": 0,
    "position": "normal",
    "style": "default",
    "label_placement": "top",
    "instruction_placement": "label",
    "hide_on_screen": "",
    "active": true,
    "description": "",
    "modified": 1628612958
}